pydebiaseddta/__init__.py
pydebiaseddta/evaluation.py
pydebiaseddta/utils.py
pydebiaseddta/visualization.py
pydebiaseddta/data/dta/dta_sample_sw_sim_matrix.csv
pydebiaseddta/data/dta/dta_sample_data/test.csv
pydebiaseddta/data/dta/dta_sample_data/train.csv
pydebiaseddta/data/dta/dta_sample_data/val.csv
pydebiaseddta/data/dta/dta_sample_data_mini/test.csv
pydebiaseddta/data/dta/dta_sample_data_mini/train.csv
pydebiaseddta/data/dta/dta_sample_data_mini/val.csv
pydebiaseddta/data/sequence/chembl27.mini.smiles
pydebiaseddta/data/word_identification/ligand_mini_test.json
pydebiaseddta/data/word_identification/ligand/chembl27_enc_94.json
pydebiaseddta/data/word_identification/ligand/chembl27_enc_bpe_8000.json
pydebiaseddta/data/word_identification/ligand/chembl27_encoding.json
pydebiaseddta/data/word_identification/protein/uniprot_26.json
pydebiaseddta/data/word_identification/protein/uniprot_bpe_32000.json
pydebiaseddta/debiasing/__init__.py
pydebiaseddta/debiasing/debiaseddta.py
pydebiaseddta/guides/__init__.py
pydebiaseddta/guides/abstract_guide.py
pydebiaseddta/guides/bowdta.py
pydebiaseddta/guides/iddta.py
pydebiaseddta/guides/outdta.py
pydebiaseddta/guides/rfdta.py
pydebiaseddta/predictors/__init__.py
pydebiaseddta/predictors/abstract_predictors.py
pydebiaseddta/predictors/bpedta.py
pydebiaseddta/predictors/deepdta.py
pydebiaseddta/predictors/lmdta.py
pydebiaseddta/sequence/__init__.py
pydebiaseddta/sequence/smiles_processing.py
pydebiaseddta/sequence/word_identification.py
pydebiaseddta-0.1.0.dist-info/LICENSE
pydebiaseddta-0.1.0.dist-info/METADATA
pydebiaseddta-0.1.0.dist-info/WHEEL
pydebiaseddta-0.1.0.dist-info/top_level.txt
pydebiaseddta-0.1.0.dist-info/RECORD
