Metadata-Version: 2.1
Name: pydebiaseddta
Version: 0.1.0
Summary: Python library to improve generalizability of the drug-target prediction models via DebiasedDTA
Author-email: Rıza Özçelik <riza.ozcelik@boun.edu.tr>
License: Copyright (c) 2023 Rıza Özçelik
Project-URL: Homepage, https://pydebiaseddta.readthedocs.io/en/latest/
Project-URL: GitHub, https://github.com/rizaozcelik/pydebiaseddta
Keywords: machine learning,computational drug discovery,cheminformatics,debiasing,affinity prediction,debiaseddta
Classifier: Programming Language :: Python :: 3
Classifier: License :: OSI Approved :: MIT License
Classifier: Operating System :: OS Independent
Requires-Python: >=3.9.7
License-File: LICENSE
Requires-Dist: numpy (==1.21.2)
Requires-Dist: scikit-learn (==1.1.1)
Requires-Dist: tensorflow (==2.7.0)
Requires-Dist: tokenizers (==0.10.3)
Requires-Dist: transformers (==4.4.0)
Requires-Dist: pandas (==1.4.4)
Requires-Dist: ipykernel (==6.15.2)
Requires-Dist: protobuf (==3.20.0)
Requires-Dist: packaging (==21.3)
Requires-Dist: rdkit (==2022.09.5)
Requires-Dist: matplotlib (==3.5.2)
